carpeta/__init__.py
carpeta/logging.py
carpeta/output.py
carpeta/trace.py
carpeta/traceable.py
carpeta/tracer.py
carpeta-0.1.0a2.dist-info/LICENSE.txt
carpeta-0.1.0a2.dist-info/METADATA
carpeta-0.1.0a2.dist-info/WHEEL
carpeta-0.1.0a2.dist-info/top_level.txt
carpeta-0.1.0a2.dist-info/RECORD
